cloudpush/Client.py
cloudpush/__init__.py
cloud_push_client-1.0.3.dist-info/LICENSE
cloud_push_client-1.0.3.dist-info/METADATA
cloud_push_client-1.0.3.dist-info/WHEEL
cloud_push_client-1.0.3.dist-info/top_level.txt
cloud_push_client-1.0.3.dist-info/RECORD
