Metadata-Version: 2.1
Name: cloud-push-client
Version: 1.0.3
Summary: A Python client for the Bluemix/IBM push notifications service
Home-page: https://github.com/AndreasDickow/CloudPushNotificationsPythonClient
Author: Andreas Dickow
Author-email: andreas.dickow@biz-factory.de
License: UNKNOWN
Platform: UNKNOWN
Classifier: Programming Language :: Python :: 3
Classifier: License :: OSI Approved :: GNU Lesser General Public License v3 (LGPLv3)
Classifier: Operating System :: OS Independent
Requires-Python: >=3.4
